README
setup.py
django_mobile_views.egg-info/PKG-INFO
django_mobile_views.egg-info/SOURCES.txt
django_mobile_views.egg-info/dependency_links.txt
django_mobile_views.egg-info/not-zip-safe
django_mobile_views.egg-info/requires.txt
django_mobile_views.egg-info/top_level.txt
mobile_views/__init__.py
mobile_views/generic_views.py
mobile_views/models.py
mobile_views/tests.py
mobile_views/urls.py
mobile_views/utilities.py
mobile_views/views.py